csvtomd.py
csvtomd/__init__.py
csvtomd/csvtomd.py
csvtomd-0.3.0.dist-info/DESCRIPTION.rst
csvtomd-0.3.0.dist-info/METADATA
csvtomd-0.3.0.dist-info/RECORD
csvtomd-0.3.0.dist-info/WHEEL
csvtomd-0.3.0.dist-info/entry_points.txt
csvtomd-0.3.0.dist-info/metadata.json
csvtomd-0.3.0.dist-info/top_level.txt
