Metadata-Version: 2.0
Name: csvtomd
Version: 0.3.0
Summary: Convert your CSV files into Markdown tables.
Home-page: https://github.com/mplewis/csvtomd
Author: Matthew Lewis
Author-email: matt@mplewis.com
License: MIT
Platform: UNKNOWN
Classifier: Development Status :: 5 - Production/Stable
Classifier: Natural Language :: English
Classifier: License :: OSI Approved :: MIT License
Classifier: Operating System :: OS Independent
Classifier: Programming Language :: Python
Classifier: Programming Language :: Python :: 3
Classifier: Programming Language :: Python :: 3.5
Classifier: Topic :: Text Processing :: Markup
